listwrap/__init__.py
listwrap-0.0.3.dist-info/LICENSE
listwrap-0.0.3.dist-info/METADATA
listwrap-0.0.3.dist-info/WHEEL
listwrap-0.0.3.dist-info/top_level.txt
listwrap-0.0.3.dist-info/RECORD
