Metadata-Version: 2.1
Name: listwrap
Version: 0.0.3
Summary: Formatting lists of strings.
Author-email: Zach Kurtz <zkurtz@gmail.com>
Project-URL: Source, https://github.com/zkurtz/listwrap
Requires-Python: >=3.10
License-File: LICENSE
